{"data":{"INFO":{"CODGRUPO":"45412812","GOLES_CASA":"2","GOLES_FUERA":"1","PENALTIS_CASA":null,"PENALTIS_FUERA":null,"CODACTA":"3109590","COD_COMPETICION":43990651,"NOM_COMPETICION":"BENJAMÍ 7 SEGONA DIVISIÓ","NOM_COMPETICION_URL":"benjami-7-segona-divisio","COD_GRUPO":45412812,"GRUPO":"GRUP 16","GRUPO_URL":"grup-16","CODEQUIPO_CASA":"42390","CODEQUIPO_FUERA":"34352","JORNADA":"5","CODIGO_CAMPO":"340","COMIENZO1":"2022-11-06 09:00:00","SUSPENDIDO":"0","NOMBRE":"CAMP DE FUTBOL CEM ARISTIDES MAILLOL","DIRECCION":"c/ de Martí i Franquès, 17-21","TEMP_NOMBRE":"2223","TEMP_LARGO":"TEMPORADA 2022-2023","CIUDAD":"Barcelona","ESTADO":"4"},"ARBITROS":[{"CODTIPO_ARBITRO":"1","CODARBITRO":"3257450","NOMBRE_ARBITRO":"ARNAU","NOMBRE":"Barcelona3"}],"GOLES":[{"NOMBRE":"URIEL","LICENCIA":"12","DORSAL":"10","CODPARTICIPANTE":"41213350","FECHA_NACIMIENTO":2,"PORTERO":null,"TIPO":"normal","MINUTO":"30","EQUIPO":"local"},{"NOMBRE":"ADRISH","LICENCIA":"12","DORSAL":"11","CODPARTICIPANTE":"41242019","FECHA_NACIMIENTO":1,"PORTERO":null,"TIPO":"normal","MINUTO":"22","EQUIPO":"local"},{"NOMBRE":"ROI","LICENCIA":"12","DORSAL":"43","CODPARTICIPANTE":"38681494","FECHA_NACIMIENTO":2,"PORTERO":null,"TIPO":"normal","MINUTO":"50","EQUIPO":"visitante"}],"EQUIPO_CASA":{"CODCLUB":6174,"CODCLUB2":6174,"CODEQUIPO":42390,"NOMBRE_CLUB":"PENYA BARC. COLLBLANC SANTS,AE","NOMBRE_CLUB_URL":"penya-barc-collblanc-sants-ae","NOMBRE_EQUIPO":"PENYA BARC. COLLBLANC SANTS,AE B","NOMBRE_EQUIPO_URL":"penya-barc-collblanc-sants-ae-b","NOMBRE":"00100_0000094725_Escudo3_1.png","NOMBRE_ABREVIADO_URL":"72b","CODGRUPO":41651818,"TITULARES":[{"NOMBRE":"MIGUEL ANGEL","LICENCIA":"12","DORSAL":"1","CODPARTICIPANTE":"44678665","FECHA_NACIMIENTO":2,"PORTERO":1},{"NOMBRE":"POL","LICENCIA":"12","DORSAL":"2","CODPARTICIPANTE":"42216646","FECHA_NACIMIENTO":1,"PORTERO":null},{"NOMBRE":"FRANKLIN","LICENCIA":"12","DORSAL":"3","CODPARTICIPANTE":"41324435","FECHA_NACIMIENTO":1,"PORTERO":null},{"NOMBRE":"JOFRE","LICENCIA":"12","DORSAL":"9","CODPARTICIPANTE":"42017383","FECHA_NACIMIENTO":1,"PORTERO":null},{"NOMBRE":"URIEL","LICENCIA":"12","DORSAL":"10","CODPARTICIPANTE":"41213350","FECHA_NACIMIENTO":2,"PORTERO":null},{"NOMBRE":"ADRISH","LICENCIA":"12","DORSAL":"11","CODPARTICIPANTE":"41242019","FECHA_NACIMIENTO":1,"PORTERO":null},{"NOMBRE":"MARC","LICENCIA":"12","DORSAL":"12","CODPARTICIPANTE":"44671382","FECHA_NACIMIENTO":1,"PORTERO":null}],"SUPLENTES":[{"NOMBRE":"MAX","LICENCIA":"15213578","DORSAL":"5","CODPARTICIPANTE":"44671851","FECHA_NACIMIENTO":1,"PORTERO":null}],"COSTECNIC":{"Entrenador Titular":"FROILAN"},"SUSTITUCIONES":[],"SANCIONES":[]},"EQUIPO_FUERA":{"CODCLUB":6178,"CODCLUB2":6178,"CODEQUIPO":34352,"NOMBRE_CLUB":"FUNDACIO P. CE. JUPITER","NOMBRE_CLUB_URL":"fundacio-p-ce-jupiter","NOMBRE_EQUIPO":"FUNDACIÓ P. CE. JÚPITER C","NOMBRE_EQUIPO_URL":"fundacio-p-ce-jupiter-c","NOMBRE":"00100_0000672019_cejupiter_200x200.png","NOMBRE_ABREVIADO_URL":"72b","CODGRUPO":42201979,"TITULARES":[{"NOMBRE":"EIDEN","LICENCIA":"12","DORSAL":"1","CODPARTICIPANTE":"36794883","FECHA_NACIMIENTO":1,"PORTERO":1},{"NOMBRE":"IAN","LICENCIA":"12","DORSAL":"33","CODPARTICIPANTE":"35113442","FECHA_NACIMIENTO":1,"PORTERO":null},{"NOMBRE":"MATIAS NICOLAS","LICENCIA":"12","DORSAL":"35","CODPARTICIPANTE":"36090920","FECHA_NACIMIENTO":1,"PORTERO":null},{"NOMBRE":"ALBERT","LICENCIA":"12","DORSAL":"37","CODPARTICIPANTE":"45997864","FECHA_NACIMIENTO":1,"PORTERO":null},{"NOMBRE":"JOEL BENEDICTO","LICENCIA":"12","DORSAL":"39","CODPARTICIPANTE":"41841064","FECHA_NACIMIENTO":2,"PORTERO":null},{"NOMBRE":"QUIM","LICENCIA":"12","DORSAL":"41","CODPARTICIPANTE":"38622006","FECHA_NACIMIENTO":1,"PORTERO":null},{"NOMBRE":"ROI","LICENCIA":"12","DORSAL":"43","CODPARTICIPANTE":"38681494","FECHA_NACIMIENTO":2,"PORTERO":null}],"SUPLENTES":[{"NOMBRE":"HUGO","LICENCIA":"12","DORSAL":"36","CODPARTICIPANTE":"45574737","FECHA_NACIMIENTO":1,"PORTERO":null},{"NOMBRE":"MARIO","LICENCIA":"12","DORSAL":"38","CODPARTICIPANTE":"36011239","FECHA_NACIMIENTO":1,"PORTERO":null}],"COSTECNIC":{"Entrenador Titular":"DAVID"},"SUSTITUCIONES":[],"SANCIONES":[]}},"codacta":"3109590","titulars_local":[{"codparticipant":44678665,"codequip":42390,"dorsal":1,"titularitats":1,"porter":1,"nom":"MIGUEL ANGEL","any":2014,"partits":1,"nom_equip":"PENYA BARC. COLLBLANC SANTS,AE B","colorequipacio1":"#222277","colorequipacio2":"#00FF00"},{"codparticipant":42216646,"codequip":42390,"dorsal":2,"titularitats":1,"porter":null,"nom":"POL","any":2013,"partits":1,"nom_equip":"PENYA BARC. COLLBLANC SANTS,AE B","colorequipacio1":"#222277","colorequipacio2":"#00FF00"},{"codparticipant":41324435,"codequip":42390,"dorsal":3,"titularitats":1,"porter":null,"nom":"FRANKLIN","any":2013,"partits":1,"nom_equip":"PENYA BARC. COLLBLANC SANTS,AE B","colorequipacio1":"#222277","colorequipacio2":"#00FF00"},{"codparticipant":44671851,"codequip":42390,"dorsal":5,"titularitats":0,"porter":null,"nom":"MAX","any":2013,"partits":1,"nom_equip":"PENYA BARC. COLLBLANC SANTS,AE B","colorequipacio1":"#222277","colorequipacio2":"#00FF00"},{"codparticipant":42017383,"codequip":42390,"dorsal":9,"titularitats":1,"porter":null,"nom":"JOFRE","any":2013,"partits":1,"nom_equip":"PENYA BARC. COLLBLANC SANTS,AE B","colorequipacio1":"#222277","colorequipacio2":"#00FF00"},{"codparticipant":41213350,"codequip":42390,"dorsal":10,"titularitats":1,"porter":null,"nom":"URIEL","any":2014,"partits":1,"nom_equip":"PENYA BARC. COLLBLANC SANTS,AE B","colorequipacio1":"#222277","colorequipacio2":"#00FF00"},{"codparticipant":41242019,"codequip":42390,"dorsal":11,"titularitats":1,"porter":null,"nom":"ADRISH","any":2013,"partits":1,"nom_equip":"PENYA BARC. COLLBLANC SANTS,AE B","colorequipacio1":"#222277","colorequipacio2":"#00FF00"},{"codparticipant":44671382,"codequip":42390,"dorsal":12,"titularitats":1,"porter":null,"nom":"MARC","any":2013,"partits":1,"nom_equip":"PENYA BARC. COLLBLANC SANTS,AE B","colorequipacio1":"#222277","colorequipacio2":"#00FF00"}],"titulars_visitant":[{"codparticipant":36794883,"codequip":34352,"dorsal":1,"titularitats":1,"porter":1,"nom":"EIDEN","any":2013,"partits":1,"nom_equip":"FUNDACIÓ P. CE. JÚPITER C","colorequipacio1":"#960202","colorequipacio2":"#FFFFFF"},{"codparticipant":35113442,"codequip":34352,"dorsal":33,"titularitats":1,"porter":null,"nom":"IAN","any":2013,"partits":1,"nom_equip":"FUNDACIÓ P. CE. JÚPITER C","colorequipacio1":"#960202","colorequipacio2":"#FFFFFF"},{"codparticipant":36090920,"codequip":34352,"dorsal":35,"titularitats":1,"porter":null,"nom":"MATIAS NICOLAS","any":2013,"partits":1,"nom_equip":"FUNDACIÓ P. CE. JÚPITER C","colorequipacio1":"#960202","colorequipacio2":"#FFFFFF"},{"codparticipant":45574737,"codequip":34352,"dorsal":36,"titularitats":0,"porter":null,"nom":"HUGO","any":2013,"partits":1,"nom_equip":"FUNDACIÓ P. CE. JÚPITER C","colorequipacio1":"#960202","colorequipacio2":"#FFFFFF"},{"codparticipant":45997864,"codequip":34352,"dorsal":37,"titularitats":1,"porter":null,"nom":"ALBERT","any":2013,"partits":1,"nom_equip":"FUNDACIÓ P. CE. JÚPITER C","colorequipacio1":"#960202","colorequipacio2":"#FFFFFF"},{"codparticipant":36011239,"codequip":34352,"dorsal":38,"titularitats":0,"porter":null,"nom":"MARIO","any":2013,"partits":1,"nom_equip":"FUNDACIÓ P. CE. JÚPITER C","colorequipacio1":"#960202","colorequipacio2":"#FFFFFF"},{"codparticipant":41841064,"codequip":34352,"dorsal":39,"titularitats":1,"porter":null,"nom":"JOEL BENEDICTO","any":2014,"partits":1,"nom_equip":"FUNDACIÓ P. CE. JÚPITER C","colorequipacio1":"#960202","colorequipacio2":"#FFFFFF"},{"codparticipant":38622006,"codequip":34352,"dorsal":41,"titularitats":1,"porter":null,"nom":"QUIM","any":2013,"partits":1,"nom_equip":"FUNDACIÓ P. CE. JÚPITER C","colorequipacio1":"#960202","colorequipacio2":"#FFFFFF"},{"codparticipant":38681494,"codequip":34352,"dorsal":43,"titularitats":1,"porter":null,"nom":"ROI","any":2014,"partits":1,"nom_equip":"FUNDACIÓ P. CE. JÚPITER C","colorequipacio1":"#960202","colorequipacio2":"#FFFFFF"}],"menuFollowTeams":[{"label":"BEN A","href":"/classificacio?id=45412613"},{"label":"BEN B","href":"/classificacio?id=45413087"},{"label":"BEN C","href":"/classificacio?id=45412812"},{"label":"BEN D","href":"/classificacio?id=45293518"},{"label":"BEN E","href":"/classificacio?id=45293333"}]}