{"data":{"INFO":{"CODGRUPO":"45412613","GOLES_CASA":"6","GOLES_FUERA":"0","PENALTIS_CASA":null,"PENALTIS_FUERA":null,"CODACTA":"3109434","COD_COMPETICION":43990651,"NOM_COMPETICION":"BENJAMÍ 7 SEGONA DIVISIÓ","NOM_COMPETICION_URL":"benjami-7-segona-divisio","COD_GRUPO":45412613,"GRUPO":"GRUP 15","GRUPO_URL":"grup-15","CODEQUIPO_CASA":"40874","CODEQUIPO_FUERA":"18472025","JORNADA":"16","CODIGO_CAMPO":"310","COMIENZO1":"2023-02-11 13:15:00","SUSPENDIDO":"0","NOMBRE":"CAMP DE FUTBOL CEM CLOT DE LA MEL","DIRECCION":"c/ d'Andrade, 40","TEMP_NOMBRE":"2223","TEMP_LARGO":"TEMPORADA 2022-2023","CIUDAD":"Barcelona","ESTADO":"4"},"ARBITROS":[{"CODTIPO_ARBITRO":"1","CODARBITRO":"3327794","NOMBRE_ARBITRO":"MARC","NOMBRE":"Barcelona3"}],"GOLES":[{"NOMBRE":"XAVIER","LICENCIA":"12","DORSAL":"32","CODPARTICIPANTE":"39084764","FECHA_NACIMIENTO":1,"PORTERO":null,"TIPO":"normal","MINUTO":"8","EQUIPO":"local"},{"NOMBRE":"XAVIER","LICENCIA":"12","DORSAL":"32","CODPARTICIPANTE":"39084764","FECHA_NACIMIENTO":1,"PORTERO":null,"TIPO":"normal","MINUTO":"10","EQUIPO":"local"},{"NOMBRE":"XAVIER","LICENCIA":"12","DORSAL":"32","CODPARTICIPANTE":"39084764","FECHA_NACIMIENTO":1,"PORTERO":null,"TIPO":"normal","MINUTO":"34","EQUIPO":"local"},{"NOMBRE":"XAVIER","LICENCIA":"12","DORSAL":"32","CODPARTICIPANTE":"39084764","FECHA_NACIMIENTO":1,"PORTERO":null,"TIPO":"normal","MINUTO":"46","EQUIPO":"local"},{"NOMBRE":"ROC","LICENCIA":"12","DORSAL":"37","CODPARTICIPANTE":"42218132","FECHA_NACIMIENTO":1,"PORTERO":null,"TIPO":"normal","MINUTO":"21","EQUIPO":"local"},{"NOMBRE":"PAU","LICENCIA":"12","DORSAL":"50","CODPARTICIPANTE":"38462101","FECHA_NACIMIENTO":1,"PORTERO":null,"TIPO":"normal","MINUTO":"36","EQUIPO":"local"}],"EQUIPO_CASA":{"CODCLUB":6237,"CODCLUB2":6237,"CODEQUIPO":40874,"NOMBRE_CLUB":"VILA OLIMPICA CLUB ESPORTIU","NOMBRE_CLUB_URL":"vila-olimpica-club-esportiu","NOMBRE_EQUIPO":"VILA OLIMPICA CLUB ESP. E","NOMBRE_EQUIPO_URL":"vila-olimpica-club-esp-e","NOMBRE":"00100_0000586311_cevo_200x200.png","NOMBRE_ABREVIADO_URL":"72b","CODGRUPO":41654451,"TITULARES":[{"NOMBRE":"ELOY","LICENCIA":"12","DORSAL":"1","CODPARTICIPANTE":"44371257","FECHA_NACIMIENTO":1,"PORTERO":1},{"NOMBRE":"GERARD","LICENCIA":"12","DORSAL":"9","CODPARTICIPANTE":"44933373","FECHA_NACIMIENTO":1,"PORTERO":null},{"NOMBRE":"UNAI","LICENCIA":"12","DORSAL":"28","CODPARTICIPANTE":"37105717","FECHA_NACIMIENTO":1,"PORTERO":null},{"NOMBRE":"XAVIER","LICENCIA":"12","DORSAL":"32","CODPARTICIPANTE":"39084764","FECHA_NACIMIENTO":1,"PORTERO":null},{"NOMBRE":"RAÚL","LICENCIA":"12","DORSAL":"43","CODPARTICIPANTE":"36096210","FECHA_NACIMIENTO":1,"PORTERO":null},{"NOMBRE":"BIEL","LICENCIA":"12","DORSAL":"45","CODPARTICIPANTE":"38463327","FECHA_NACIMIENTO":1,"PORTERO":null},{"NOMBRE":"PAU","LICENCIA":"12","DORSAL":"50","CODPARTICIPANTE":"38462101","FECHA_NACIMIENTO":1,"PORTERO":null}],"SUPLENTES":[{"NOMBRE":"ROC","LICENCIA":"12","DORSAL":"37","CODPARTICIPANTE":"42218132","FECHA_NACIMIENTO":1,"PORTERO":null}],"COSTECNIC":{"Delegat":"POL","Entrenador Titular":"MAX"},"SUSTITUCIONES":[],"SANCIONES":[]},"EQUIPO_FUERA":{"CODCLUB":1224,"CODCLUB2":1224,"CODEQUIPO":18472025,"NOMBRE_CLUB":"ESCOLA E.BRAFA","NOMBRE_CLUB_URL":"escola-ebrafa","NOMBRE_EQUIPO":"ESCOLA E.BRAFA  A","NOMBRE_EQUIPO_URL":"escola-ebrafa-a","NOMBRE":"00100_0000814734_brafa_200.png","NOMBRE_ABREVIADO_URL":"72b","CODGRUPO":41654626,"TITULARES":[{"NOMBRE":"DANIEL","LICENCIA":"12","DORSAL":"1","CODPARTICIPANTE":"45426475","FECHA_NACIMIENTO":2,"PORTERO":1},{"NOMBRE":"MIGUEL","LICENCIA":"12","DORSAL":"8","CODPARTICIPANTE":"45312529","FECHA_NACIMIENTO":2,"PORTERO":null},{"NOMBRE":"AARON","LICENCIA":"12","DORSAL":"9","CODPARTICIPANTE":"45312401","FECHA_NACIMIENTO":2,"PORTERO":null},{"NOMBRE":"ALEX","LICENCIA":"12","DORSAL":"10","CODPARTICIPANTE":"45426792","FECHA_NACIMIENTO":2,"PORTERO":null},{"NOMBRE":"HUGO","LICENCIA":"12","DORSAL":"14","CODPARTICIPANTE":"45312756","FECHA_NACIMIENTO":2,"PORTERO":null},{"NOMBRE":"IZAN ALEJANDRO","LICENCIA":"12","DORSAL":"15","CODPARTICIPANTE":"45312081","FECHA_NACIMIENTO":2,"PORTERO":null},{"NOMBRE":"HUGO","LICENCIA":"12","DORSAL":"20","CODPARTICIPANTE":"45738717","FECHA_NACIMIENTO":1,"PORTERO":null}],"SUPLENTES":[{"NOMBRE":"BIEL","LICENCIA":"12","DORSAL":"19","CODPARTICIPANTE":"45104894","FECHA_NACIMIENTO":2,"PORTERO":null},{"NOMBRE":"BACAR IVAN","LICENCIA":"12","DORSAL":"21","CODPARTICIPANTE":"46064823","FECHA_NACIMIENTO":1,"PORTERO":null}],"COSTECNIC":{"Entrenador Titular":"ARNAU"},"SUSTITUCIONES":[],"SANCIONES":[]}},"codacta":"3109434","titulars_local":[{"codparticipant":44371257,"codequip":40874,"dorsal":1,"titularitats":1,"porter":1,"nom":"ELOY","any":2013,"partits":1,"nom_equip":"VILA OLIMPICA CLUB ESP. E","colorequipacio1":"#2148D9","colorequipacio2":"#FFFF06"},{"codparticipant":44933373,"codequip":40874,"dorsal":9,"titularitats":1,"porter":null,"nom":"GERARD","any":2013,"partits":1,"nom_equip":"VILA OLIMPICA CLUB ESP. E","colorequipacio1":"#2148D9","colorequipacio2":"#FFFF06"},{"codparticipant":37105717,"codequip":40874,"dorsal":28,"titularitats":1,"porter":null,"nom":"UNAI","any":2013,"partits":1,"nom_equip":"VILA OLIMPICA CLUB ESP. E","colorequipacio1":"#2148D9","colorequipacio2":"#FFFF06"},{"codparticipant":39084764,"codequip":40874,"dorsal":32,"titularitats":1,"porter":null,"nom":"XAVIER","any":2013,"partits":1,"nom_equip":"VILA OLIMPICA CLUB ESP. E","colorequipacio1":"#2148D9","colorequipacio2":"#FFFF06"},{"codparticipant":42218132,"codequip":40874,"dorsal":37,"titularitats":0,"porter":null,"nom":"ROC","any":2013,"partits":1,"nom_equip":"VILA OLIMPICA CLUB ESP. E","colorequipacio1":"#2148D9","colorequipacio2":"#FFFF06"},{"codparticipant":36096210,"codequip":40874,"dorsal":43,"titularitats":1,"porter":null,"nom":"RAÚL","any":2013,"partits":1,"nom_equip":"VILA OLIMPICA CLUB ESP. E","colorequipacio1":"#2148D9","colorequipacio2":"#FFFF06"},{"codparticipant":38463327,"codequip":40874,"dorsal":45,"titularitats":1,"porter":null,"nom":"BIEL","any":2013,"partits":1,"nom_equip":"VILA OLIMPICA CLUB ESP. E","colorequipacio1":"#2148D9","colorequipacio2":"#FFFF06"},{"codparticipant":38462101,"codequip":40874,"dorsal":50,"titularitats":1,"porter":null,"nom":"PAU","any":2013,"partits":1,"nom_equip":"VILA OLIMPICA CLUB ESP. E","colorequipacio1":"#2148D9","colorequipacio2":"#FFFF06"}],"titulars_visitant":[{"codparticipant":45426475,"codequip":18472025,"dorsal":1,"titularitats":1,"porter":1,"nom":"DANIEL","any":2014,"partits":1,"nom_equip":"ESCOLA E.BRAFA  A","colorequipacio1":"#0000FF","colorequipacio2":"#FF0000"},{"codparticipant":45312529,"codequip":18472025,"dorsal":8,"titularitats":1,"porter":null,"nom":"MIGUEL","any":2014,"partits":1,"nom_equip":"ESCOLA E.BRAFA  A","colorequipacio1":"#0000FF","colorequipacio2":"#FF0000"},{"codparticipant":45312401,"codequip":18472025,"dorsal":9,"titularitats":1,"porter":null,"nom":"AARON","any":2014,"partits":1,"nom_equip":"ESCOLA E.BRAFA  A","colorequipacio1":"#0000FF","colorequipacio2":"#FF0000"},{"codparticipant":45426792,"codequip":18472025,"dorsal":10,"titularitats":1,"porter":null,"nom":"ALEX","any":2014,"partits":1,"nom_equip":"ESCOLA E.BRAFA  A","colorequipacio1":"#0000FF","colorequipacio2":"#FF0000"},{"codparticipant":45312756,"codequip":18472025,"dorsal":14,"titularitats":1,"porter":null,"nom":"HUGO","any":2014,"partits":1,"nom_equip":"ESCOLA E.BRAFA  A","colorequipacio1":"#0000FF","colorequipacio2":"#FF0000"},{"codparticipant":45312081,"codequip":18472025,"dorsal":15,"titularitats":1,"porter":null,"nom":"IZAN ALEJANDRO","any":2014,"partits":1,"nom_equip":"ESCOLA E.BRAFA  A","colorequipacio1":"#0000FF","colorequipacio2":"#FF0000"},{"codparticipant":45104894,"codequip":18472025,"dorsal":19,"titularitats":0,"porter":null,"nom":"BIEL","any":2014,"partits":1,"nom_equip":"ESCOLA E.BRAFA  A","colorequipacio1":"#0000FF","colorequipacio2":"#FF0000"},{"codparticipant":45738717,"codequip":18472025,"dorsal":20,"titularitats":1,"porter":null,"nom":"HUGO","any":2013,"partits":1,"nom_equip":"ESCOLA E.BRAFA  A","colorequipacio1":"#0000FF","colorequipacio2":"#FF0000"},{"codparticipant":46064823,"codequip":18472025,"dorsal":21,"titularitats":0,"porter":null,"nom":"BACAR IVAN","any":2013,"partits":1,"nom_equip":"ESCOLA E.BRAFA  A","colorequipacio1":"#0000FF","colorequipacio2":"#FF0000"}],"menuFollowTeams":[{"label":"BEN A","href":"/classificacio?id=45412613"},{"label":"BEN B","href":"/classificacio?id=45413087"},{"label":"BEN C","href":"/classificacio?id=45412812"},{"label":"BEN D","href":"/classificacio?id=45293518"},{"label":"BEN E","href":"/classificacio?id=45293333"}]}