{"data":{"INFO":{"CODGRUPO":"45412812","GOLES_CASA":"2","GOLES_FUERA":"1","PENALTIS_CASA":null,"PENALTIS_FUERA":null,"CODACTA":"3109784","COD_COMPETICION":43990651,"NOM_COMPETICION":"BENJAMÍ 7 SEGONA DIVISIÓ","NOM_COMPETICION_URL":"benjami-7-segona-divisio","COD_GRUPO":45412812,"GRUPO":"GRUP 16","GRUPO_URL":"grup-16","CODEQUIPO_CASA":"15544692","CODEQUIPO_FUERA":"22745737","JORNADA":"30","CODIGO_CAMPO":"981","COMIENZO1":"2023-06-03 12:00:00","SUSPENDIDO":"0","NOMBRE":"CAMP DE FUTBOL CLUB MEILAND","DIRECCION":"c/ de la Maternitat d'Elna, s/n","TEMP_NOMBRE":"2223","TEMP_LARGO":"TEMPORADA 2022-2023","CIUDAD":"Barcelona","ESTADO":"4"},"ARBITROS":[{"CODTIPO_ARBITRO":"1","CODARBITRO":"3388235","NOMBRE_ARBITRO":"POL","NOMBRE":"Barcelona3"}],"GOLES":[{"NOMBRE":"ALEX","LICENCIA":"12","DORSAL":"5","CODPARTICIPANTE":"39900022","FECHA_NACIMIENTO":1,"PORTERO":null,"TIPO":"normal","MINUTO":"35","EQUIPO":"visitante"},{"NOMBRE":"YAGO","LICENCIA":"12","DORSAL":"7","CODPARTICIPANTE":"36280982","FECHA_NACIMIENTO":1,"PORTERO":null,"TIPO":"normal","MINUTO":"26","EQUIPO":"local"},{"NOMBRE":"GERARD","LICENCIA":"12","DORSAL":"19","CODPARTICIPANTE":"34215472","FECHA_NACIMIENTO":1,"PORTERO":null,"TIPO":"normal","MINUTO":"12","EQUIPO":"local"}],"EQUIPO_CASA":{"CODCLUB":6433,"CODCLUB2":15543656,"CODEQUIPO":15544692,"NOMBRE_CLUB":"TECNOFUTBOL C.F.","NOMBRE_CLUB_URL":"tecnofutbol-cf","NOMBRE_EQUIPO":"TECNOFUTBOL C.F A","NOMBRE_EQUIPO_URL":"tecnofutbol-cf-a","NOMBRE":"00100_0000034722_tecnofutbol.png","NOMBRE_ABREVIADO_URL":"72b","CODGRUPO":41654285,"TITULARES":[{"NOMBRE":"YAGO","LICENCIA":"12","DORSAL":"7","CODPARTICIPANTE":"36280982","FECHA_NACIMIENTO":1,"PORTERO":null},{"NOMBRE":"ROGER","LICENCIA":"12","DORSAL":"8","CODPARTICIPANTE":"38709173","FECHA_NACIMIENTO":1,"PORTERO":null},{"NOMBRE":"HÉCTOR","LICENCIA":"12","DORSAL":"13","CODPARTICIPANTE":"39088373","FECHA_NACIMIENTO":1,"PORTERO":1},{"NOMBRE":"CESC","LICENCIA":"12","DORSAL":"14","CODPARTICIPANTE":"38705746","FECHA_NACIMIENTO":2,"PORTERO":null},{"NOMBRE":"ARYAMAN","LICENCIA":"12","DORSAL":"18","CODPARTICIPANTE":"45585975","FECHA_NACIMIENTO":1,"PORTERO":null},{"NOMBRE":"GERARD","LICENCIA":"12","DORSAL":"19","CODPARTICIPANTE":"34215472","FECHA_NACIMIENTO":1,"PORTERO":null},{"NOMBRE":"ANDREU","LICENCIA":"12","DORSAL":"20","CODPARTICIPANTE":"35955142","FECHA_NACIMIENTO":1,"PORTERO":null}],"SUPLENTES":[{"NOMBRE":"HUGO","LICENCIA":"12","DORSAL":"16","CODPARTICIPANTE":"36448465","FECHA_NACIMIENTO":1,"PORTERO":null},{"NOMBRE":"POL","LICENCIA":"12","DORSAL":"17","CODPARTICIPANTE":"39295468","FECHA_NACIMIENTO":1,"PORTERO":null}],"COSTECNIC":{"Entrenador Titular":"ROGER"},"SUSTITUCIONES":[],"SANCIONES":[]},"EQUIPO_FUERA":{"CODCLUB":6445,"CODCLUB2":15548283,"CODEQUIPO":22745737,"NOMBRE_CLUB":"ESCOLA DE FUTBOL PREMIER BARCELONA","NOMBRE_CLUB_URL":"escola-de-futbol-premier-barcelona","NOMBRE_EQUIPO":"ESCOLA DE FUTBOL PREMIER BARCELONA D","NOMBRE_EQUIPO_URL":"escola-de-futbol-premier-barcelona-d","NOMBRE":"00100_0000754057_premierbcn_200x200.png","NOMBRE_ABREVIADO_URL":"72b","CODGRUPO":41651818,"TITULARES":[{"NOMBRE":"NIL","LICENCIA":"12","DORSAL":"1","CODPARTICIPANTE":"44283537","FECHA_NACIMIENTO":1,"PORTERO":1},{"NOMBRE":"ALEX","LICENCIA":"12","DORSAL":"5","CODPARTICIPANTE":"39900022","FECHA_NACIMIENTO":1,"PORTERO":null},{"NOMBRE":"FERNANDO MOISES","LICENCIA":"12","DORSAL":"8","CODPARTICIPANTE":"36614312","FECHA_NACIMIENTO":1,"PORTERO":null},{"NOMBRE":"ALEKSANDER","LICENCIA":"12","DORSAL":"9","CODPARTICIPANTE":"41759676","FECHA_NACIMIENTO":2,"PORTERO":null},{"NOMBRE":"OTTO","LICENCIA":"12","DORSAL":"10","CODPARTICIPANTE":"35050093","FECHA_NACIMIENTO":1,"PORTERO":null},{"NOMBRE":"CRISTHIAN DIEGO","LICENCIA":"12","DORSAL":"12","CODPARTICIPANTE":"35071205","FECHA_NACIMIENTO":1,"PORTERO":null},{"NOMBRE":"HUGO","LICENCIA":"12","DORSAL":"14","CODPARTICIPANTE":"38847783","FECHA_NACIMIENTO":1,"PORTERO":null}],"SUPLENTES":[{"NOMBRE":"GABRIEL ALEXANDER","LICENCIA":"12","DORSAL":"7","CODPARTICIPANTE":"39073050","FECHA_NACIMIENTO":2,"PORTERO":null},{"NOMBRE":"VICTOR","LICENCIA":"24","DORSAL":"71","CODPARTICIPANTE":"40399712","FECHA_NACIMIENTO":1,"PORTERO":null}],"COSTECNIC":{"Delegat":"DAVID","Entrenador Titular":"ADRIÀ","":"ARNAU"},"SUSTITUCIONES":[],"SANCIONES":[]}},"codacta":"3109784","titulars_local":[{"codparticipant":36280982,"codequip":15544692,"dorsal":7,"titularitats":1,"porter":null,"nom":"YAGO","any":2013,"partits":1,"nom_equip":"TECNOFUTBOL C.F A","colorequipacio1":"#20248B","colorequipacio2":"#800000"},{"codparticipant":38709173,"codequip":15544692,"dorsal":8,"titularitats":1,"porter":null,"nom":"ROGER","any":2013,"partits":1,"nom_equip":"TECNOFUTBOL C.F A","colorequipacio1":"#20248B","colorequipacio2":"#800000"},{"codparticipant":39088373,"codequip":15544692,"dorsal":13,"titularitats":1,"porter":1,"nom":"HÉCTOR","any":2013,"partits":1,"nom_equip":"TECNOFUTBOL C.F A","colorequipacio1":"#20248B","colorequipacio2":"#800000"},{"codparticipant":38705746,"codequip":15544692,"dorsal":14,"titularitats":1,"porter":null,"nom":"CESC","any":2014,"partits":1,"nom_equip":"TECNOFUTBOL C.F A","colorequipacio1":"#20248B","colorequipacio2":"#800000"},{"codparticipant":36448465,"codequip":15544692,"dorsal":16,"titularitats":0,"porter":null,"nom":"HUGO","any":2013,"partits":1,"nom_equip":"TECNOFUTBOL C.F A","colorequipacio1":"#20248B","colorequipacio2":"#800000"},{"codparticipant":39295468,"codequip":15544692,"dorsal":17,"titularitats":0,"porter":null,"nom":"POL","any":2013,"partits":1,"nom_equip":"TECNOFUTBOL C.F A","colorequipacio1":"#20248B","colorequipacio2":"#800000"},{"codparticipant":45585975,"codequip":15544692,"dorsal":18,"titularitats":1,"porter":null,"nom":"ARYAMAN","any":2013,"partits":1,"nom_equip":"TECNOFUTBOL C.F A","colorequipacio1":"#20248B","colorequipacio2":"#800000"},{"codparticipant":34215472,"codequip":15544692,"dorsal":19,"titularitats":1,"porter":null,"nom":"GERARD","any":2013,"partits":1,"nom_equip":"TECNOFUTBOL C.F A","colorequipacio1":"#20248B","colorequipacio2":"#800000"},{"codparticipant":35955142,"codequip":15544692,"dorsal":20,"titularitats":1,"porter":null,"nom":"ANDREU","any":2013,"partits":1,"nom_equip":"TECNOFUTBOL C.F A","colorequipacio1":"#20248B","colorequipacio2":"#800000"}],"titulars_visitant":[{"codparticipant":44283537,"codequip":22745737,"dorsal":1,"titularitats":1,"porter":1,"nom":"NIL","any":2013,"partits":1,"nom_equip":"ESCOLA DE FUTBOL PREMIER BARCELONA D","colorequipacio1":"#FF0000","colorequipacio2":"#FFFF00"},{"codparticipant":39900022,"codequip":22745737,"dorsal":5,"titularitats":1,"porter":null,"nom":"ALEX","any":2013,"partits":1,"nom_equip":"ESCOLA DE FUTBOL PREMIER BARCELONA D","colorequipacio1":"#FF0000","colorequipacio2":"#FFFF00"},{"codparticipant":39073050,"codequip":22745737,"dorsal":7,"titularitats":0,"porter":null,"nom":"GABRIEL ALEXANDER","any":2014,"partits":1,"nom_equip":"ESCOLA DE FUTBOL PREMIER BARCELONA D","colorequipacio1":"#FF0000","colorequipacio2":"#FFFF00"},{"codparticipant":36614312,"codequip":22745737,"dorsal":8,"titularitats":1,"porter":null,"nom":"FERNANDO MOISES","any":2013,"partits":1,"nom_equip":"ESCOLA DE FUTBOL PREMIER BARCELONA D","colorequipacio1":"#FF0000","colorequipacio2":"#FFFF00"},{"codparticipant":41759676,"codequip":22745737,"dorsal":9,"titularitats":1,"porter":null,"nom":"ALEKSANDER","any":2014,"partits":1,"nom_equip":"ESCOLA DE FUTBOL PREMIER BARCELONA D","colorequipacio1":"#FF0000","colorequipacio2":"#FFFF00"},{"codparticipant":35050093,"codequip":22745737,"dorsal":10,"titularitats":1,"porter":null,"nom":"OTTO","any":2013,"partits":1,"nom_equip":"ESCOLA DE FUTBOL PREMIER BARCELONA D","colorequipacio1":"#FF0000","colorequipacio2":"#FFFF00"},{"codparticipant":35071205,"codequip":22745737,"dorsal":12,"titularitats":1,"porter":null,"nom":"CRISTHIAN DIEGO","any":2013,"partits":1,"nom_equip":"ESCOLA DE FUTBOL PREMIER BARCELONA D","colorequipacio1":"#FF0000","colorequipacio2":"#FFFF00"},{"codparticipant":38847783,"codequip":22745737,"dorsal":14,"titularitats":1,"porter":null,"nom":"HUGO","any":2013,"partits":1,"nom_equip":"ESCOLA DE FUTBOL PREMIER BARCELONA D","colorequipacio1":"#FF0000","colorequipacio2":"#FFFF00"},{"codparticipant":40399712,"codequip":22745737,"dorsal":71,"titularitats":0,"porter":null,"nom":"VICTOR","any":2013,"partits":1,"nom_equip":"ESCOLA DE FUTBOL PREMIER BARCELONA D","colorequipacio1":"#FF0000","colorequipacio2":"#FFFF00"}],"menuFollowTeams":[{"label":"BEN A","href":"/classificacio?id=45412613"},{"label":"BEN B","href":"/classificacio?id=45413087"},{"label":"BEN C","href":"/classificacio?id=45412812"},{"label":"BEN D","href":"/classificacio?id=45293518"},{"label":"BEN E","href":"/classificacio?id=45293333"}]}