{"data":{"INFO":{"CODGRUPO":"45412812","GOLES_CASA":"2","GOLES_FUERA":"3","PENALTIS_CASA":null,"PENALTIS_FUERA":null,"CODACTA":"3109698","COD_COMPETICION":43990651,"NOM_COMPETICION":"BENJAMÍ 7 SEGONA DIVISIÓ","NOM_COMPETICION_URL":"benjami-7-segona-divisio","COD_GRUPO":45412812,"GRUPO":"GRUP 16","GRUPO_URL":"grup-16","CODEQUIPO_CASA":"37854","CODEQUIPO_FUERA":"36383","JORNADA":"19","CODIGO_CAMPO":"65","COMIENZO1":"2023-03-11 11:45:00","SUSPENDIDO":"0","NOMBRE":"CAMP DE FUTBOL CEM CAN DRAGO","DIRECCION":"pg. d'Andreu Nin, 2-4","TEMP_NOMBRE":"2223","TEMP_LARGO":"TEMPORADA 2022-2023","CIUDAD":"Barcelona","ESTADO":"4"},"ARBITROS":[{"CODTIPO_ARBITRO":"1","CODARBITRO":"9219","NOMBRE_ARBITRO":"HASEEB","NOMBRE":"Barcelona3"}],"GOLES":[{"NOMBRE":"ADAM","LICENCIA":"12","DORSAL":"5","CODPARTICIPANTE":"44255110","FECHA_NACIMIENTO":2,"PORTERO":null,"TIPO":"normal","MINUTO":"2","EQUIPO":"visitante"},{"NOMBRE":"ADAM","LICENCIA":"12","DORSAL":"5","CODPARTICIPANTE":"44255110","FECHA_NACIMIENTO":2,"PORTERO":null,"TIPO":"normal","MINUTO":"28","EQUIPO":"visitante"},{"NOMBRE":"ENRIC","LICENCIA":"12","DORSAL":"8","CODPARTICIPANTE":"41959461","FECHA_NACIMIENTO":1,"PORTERO":null,"TIPO":"normal","MINUTO":"32","EQUIPO":"visitante"},{"NOMBRE":"IVAN","LICENCIA":"12","DORSAL":"9","CODPARTICIPANTE":"36618596","FECHA_NACIMIENTO":1,"PORTERO":null,"TIPO":"normal","MINUTO":"4","EQUIPO":"local"},{"NOMBRE":"IVAN","LICENCIA":"12","DORSAL":"9","CODPARTICIPANTE":"36618596","FECHA_NACIMIENTO":1,"PORTERO":null,"TIPO":"normal","MINUTO":"45","EQUIPO":"local"}],"EQUIPO_CASA":{"CODCLUB":1696,"CODCLUB2":1696,"CODEQUIPO":37854,"NOMBRE_CLUB":"ALZAMORA, C.F.","NOMBRE_CLUB_URL":"alzamora-cf","NOMBRE_EQUIPO":"ALZAMORA, C.F. B","NOMBRE_EQUIPO_URL":"alzamora-cf-b","NOMBRE":"00100_0000484779_ALZAMORA,_C.F._copia.png","NOMBRE_ABREVIADO_URL":"72b","CODGRUPO":42201373,"TITULARES":[{"NOMBRE":"GERARD","LICENCIA":"12","DORSAL":"1","CODPARTICIPANTE":"39278962","FECHA_NACIMIENTO":2,"PORTERO":1},{"NOMBRE":"DYLAN","LICENCIA":"12","DORSAL":"2","CODPARTICIPANTE":"46502274","FECHA_NACIMIENTO":1,"PORTERO":null},{"NOMBRE":"DIEGO","LICENCIA":"12","DORSAL":"4","CODPARTICIPANTE":"35057614","FECHA_NACIMIENTO":1,"PORTERO":null},{"NOMBRE":"ASIER","LICENCIA":"12","DORSAL":"7","CODPARTICIPANTE":"35326919","FECHA_NACIMIENTO":1,"PORTERO":null},{"NOMBRE":"IVAN","LICENCIA":"12","DORSAL":"9","CODPARTICIPANTE":"36618596","FECHA_NACIMIENTO":1,"PORTERO":null},{"NOMBRE":"KIRILL","LICENCIA":"12","DORSAL":"10","CODPARTICIPANTE":"45092110","FECHA_NACIMIENTO":1,"PORTERO":null},{"NOMBRE":"JACKSON","LICENCIA":"12","DORSAL":"14","CODPARTICIPANTE":"35058077","FECHA_NACIMIENTO":1,"PORTERO":null}],"SUPLENTES":[{"NOMBRE":"SEBASTIAN","LICENCIA":"12","DORSAL":"5","CODPARTICIPANTE":"36485633","FECHA_NACIMIENTO":1,"PORTERO":null},{"NOMBRE":"NICOLAS","LICENCIA":"12","DORSAL":"8","CODPARTICIPANTE":"46108215","FECHA_NACIMIENTO":1,"PORTERO":null}],"COSTECNIC":{"Entrenador Titular":"DAVID"},"SUSTITUCIONES":[],"SANCIONES":[]},"EQUIPO_FUERA":{"CODCLUB":1162,"CODCLUB2":1162,"CODEQUIPO":36383,"NOMBRE_CLUB":"CATALONIA, U.B.","NOMBRE_CLUB_URL":"catalonia-ub","NOMBRE_EQUIPO":"CATALÒNIA, U.B. A","NOMBRE_EQUIPO_URL":"catalonia-ub-a","NOMBRE":"00100_0000675978_catalonia_200x200.png","NOMBRE_ABREVIADO_URL":"72b","CODGRUPO":41653927,"TITULARES":[{"NOMBRE":"SERGIO","LICENCIA":"12","DORSAL":"1","CODPARTICIPANTE":"42569338","FECHA_NACIMIENTO":1,"PORTERO":1},{"NOMBRE":"KOUICHIROU","LICENCIA":"12","DORSAL":"4","CODPARTICIPANTE":"41959992","FECHA_NACIMIENTO":1,"PORTERO":null},{"NOMBRE":"ADAM","LICENCIA":"12","DORSAL":"5","CODPARTICIPANTE":"44255110","FECHA_NACIMIENTO":2,"PORTERO":null},{"NOMBRE":"LLUC","LICENCIA":"12","DORSAL":"6","CODPARTICIPANTE":"41960173","FECHA_NACIMIENTO":1,"PORTERO":null},{"NOMBRE":"ENRIC","LICENCIA":"12","DORSAL":"8","CODPARTICIPANTE":"41959461","FECHA_NACIMIENTO":1,"PORTERO":null},{"NOMBRE":"LIONEL","LICENCIA":"12","DORSAL":"9","CODPARTICIPANTE":"38845823","FECHA_NACIMIENTO":1,"PORTERO":null},{"NOMBRE":"MARC","LICENCIA":"12","DORSAL":"10","CODPARTICIPANTE":"38846545","FECHA_NACIMIENTO":1,"PORTERO":null}],"SUPLENTES":[{"NOMBRE":"DANIEL","LICENCIA":"12","DORSAL":"2","CODPARTICIPANTE":"44254630","FECHA_NACIMIENTO":2,"PORTERO":null},{"NOMBRE":"BIEL","LICENCIA":"12","DORSAL":"7","CODPARTICIPANTE":"38846816","FECHA_NACIMIENTO":1,"PORTERO":null}],"COSTECNIC":{"Delegat":"MIQUEL","Entrenador Titular":"MARC"},"SUSTITUCIONES":[],"SANCIONES":[]}},"codacta":"3109698","titulars_local":[{"codparticipant":39278962,"codequip":37854,"dorsal":1,"titularitats":1,"porter":1,"nom":"GERARD","any":2014,"partits":1,"nom_equip":"ALZAMORA, C.F. B","colorequipacio1":"#FFFFFF","colorequipacio2":"#222222"},{"codparticipant":46502274,"codequip":37854,"dorsal":2,"titularitats":1,"porter":null,"nom":"DYLAN","any":2013,"partits":1,"nom_equip":"ALZAMORA, C.F. B","colorequipacio1":"#FFFFFF","colorequipacio2":"#222222"},{"codparticipant":35057614,"codequip":37854,"dorsal":4,"titularitats":1,"porter":null,"nom":"DIEGO","any":2013,"partits":1,"nom_equip":"ALZAMORA, C.F. B","colorequipacio1":"#FFFFFF","colorequipacio2":"#222222"},{"codparticipant":36485633,"codequip":37854,"dorsal":5,"titularitats":0,"porter":null,"nom":"SEBASTIAN","any":2013,"partits":1,"nom_equip":"ALZAMORA, C.F. B","colorequipacio1":"#FFFFFF","colorequipacio2":"#222222"},{"codparticipant":35326919,"codequip":37854,"dorsal":7,"titularitats":1,"porter":null,"nom":"ASIER","any":2013,"partits":1,"nom_equip":"ALZAMORA, C.F. B","colorequipacio1":"#FFFFFF","colorequipacio2":"#222222"},{"codparticipant":46108215,"codequip":37854,"dorsal":8,"titularitats":0,"porter":null,"nom":"NICOLAS","any":2013,"partits":1,"nom_equip":"ALZAMORA, C.F. B","colorequipacio1":"#FFFFFF","colorequipacio2":"#222222"},{"codparticipant":36618596,"codequip":37854,"dorsal":9,"titularitats":1,"porter":null,"nom":"IVAN","any":2013,"partits":1,"nom_equip":"ALZAMORA, C.F. B","colorequipacio1":"#FFFFFF","colorequipacio2":"#222222"},{"codparticipant":45092110,"codequip":37854,"dorsal":10,"titularitats":1,"porter":null,"nom":"KIRILL","any":2013,"partits":1,"nom_equip":"ALZAMORA, C.F. B","colorequipacio1":"#FFFFFF","colorequipacio2":"#222222"},{"codparticipant":35058077,"codequip":37854,"dorsal":14,"titularitats":1,"porter":null,"nom":"JACKSON","any":2013,"partits":1,"nom_equip":"ALZAMORA, C.F. B","colorequipacio1":"#FFFFFF","colorequipacio2":"#222222"}],"titulars_visitant":[{"codparticipant":42569338,"codequip":36383,"dorsal":1,"titularitats":1,"porter":1,"nom":"SERGIO","any":2013,"partits":1,"nom_equip":"CATALÒNIA, U.B. A","colorequipacio1":"#FFFFFF","colorequipacio2":"#000095"},{"codparticipant":44254630,"codequip":36383,"dorsal":2,"titularitats":0,"porter":null,"nom":"DANIEL","any":2014,"partits":1,"nom_equip":"CATALÒNIA, U.B. A","colorequipacio1":"#FFFFFF","colorequipacio2":"#000095"},{"codparticipant":41959992,"codequip":36383,"dorsal":4,"titularitats":1,"porter":null,"nom":"KOUICHIROU","any":2013,"partits":1,"nom_equip":"CATALÒNIA, U.B. A","colorequipacio1":"#FFFFFF","colorequipacio2":"#000095"},{"codparticipant":44255110,"codequip":36383,"dorsal":5,"titularitats":1,"porter":null,"nom":"ADAM","any":2014,"partits":1,"nom_equip":"CATALÒNIA, U.B. A","colorequipacio1":"#FFFFFF","colorequipacio2":"#000095"},{"codparticipant":41960173,"codequip":36383,"dorsal":6,"titularitats":1,"porter":null,"nom":"LLUC","any":2013,"partits":1,"nom_equip":"CATALÒNIA, U.B. A","colorequipacio1":"#FFFFFF","colorequipacio2":"#000095"},{"codparticipant":38846816,"codequip":36383,"dorsal":7,"titularitats":0,"porter":null,"nom":"BIEL","any":2013,"partits":1,"nom_equip":"CATALÒNIA, U.B. A","colorequipacio1":"#FFFFFF","colorequipacio2":"#000095"},{"codparticipant":41959461,"codequip":36383,"dorsal":8,"titularitats":1,"porter":null,"nom":"ENRIC","any":2013,"partits":1,"nom_equip":"CATALÒNIA, U.B. A","colorequipacio1":"#FFFFFF","colorequipacio2":"#000095"},{"codparticipant":38845823,"codequip":36383,"dorsal":9,"titularitats":1,"porter":null,"nom":"LIONEL","any":2013,"partits":1,"nom_equip":"CATALÒNIA, U.B. A","colorequipacio1":"#FFFFFF","colorequipacio2":"#000095"},{"codparticipant":38846545,"codequip":36383,"dorsal":10,"titularitats":1,"porter":null,"nom":"MARC","any":2013,"partits":1,"nom_equip":"CATALÒNIA, U.B. A","colorequipacio1":"#FFFFFF","colorequipacio2":"#000095"}],"menuFollowTeams":[{"label":"BEN A","href":"/classificacio?id=45412613"},{"label":"BEN B","href":"/classificacio?id=45413087"},{"label":"BEN C","href":"/classificacio?id=45412812"},{"label":"BEN D","href":"/classificacio?id=45293518"},{"label":"BEN E","href":"/classificacio?id=45293333"}]}