{"data":{"INFO":{"CODGRUPO":"45413087","GOLES_CASA":"2","GOLES_FUERA":"3","PENALTIS_CASA":null,"PENALTIS_FUERA":null,"CODACTA":"3110079","COD_COMPETICION":43990651,"NOM_COMPETICION":"BENJAMÍ 7 SEGONA DIVISIÓ","NOM_COMPETICION_URL":"benjami-7-segona-divisio","COD_GRUPO":45413087,"GRUPO":"GRUP 18","GRUPO_URL":"grup-18","CODEQUIPO_CASA":"18493294","CODEQUIPO_FUERA":"38045","JORNADA":"1","CODIGO_CAMPO":"688","COMIENZO1":"2022-10-09 09:00:00","SUSPENDIDO":"0","NOMBRE":"CAMP DE FUTBOL MPAL. VALL D'HEBRON","DIRECCION":"c/ de la Granja Vella, 10","TEMP_NOMBRE":"2223","TEMP_LARGO":"TEMPORADA 2022-2023","CIUDAD":"Barcelona","ESTADO":"4"},"ARBITROS":[{"CODTIPO_ARBITRO":"1","CODARBITRO":"3327640","NOMBRE_ARBITRO":"ALEX","NOMBRE":"Barcelona3"}],"GOLES":[{"NOMBRE":"BRUNO","LICENCIA":"12","DORSAL":"6","CODPARTICIPANTE":"40278081","FECHA_NACIMIENTO":1,"PORTERO":null,"TIPO":"normal","MINUTO":"5","EQUIPO":"visitante"},{"NOMBRE":"BRUNO","LICENCIA":"12","DORSAL":"6","CODPARTICIPANTE":"40278081","FECHA_NACIMIENTO":1,"PORTERO":null,"TIPO":"normal","MINUTO":"7","EQUIPO":"visitante"},{"NOMBRE":"MARTI","LICENCIA":"12","DORSAL":"10","CODPARTICIPANTE":"41161641","FECHA_NACIMIENTO":2,"PORTERO":null,"TIPO":"normal","MINUTO":"1","EQUIPO":"local"},{"NOMBRE":"ALBERT","LICENCIA":"12","DORSAL":"10","CODPARTICIPANTE":"45021396","FECHA_NACIMIENTO":1,"PORTERO":null,"TIPO":"normal","MINUTO":"8","EQUIPO":"visitante"},{"NOMBRE":"OLIVER","LICENCIA":"12","DORSAL":"16","CODPARTICIPANTE":"38402178","FECHA_NACIMIENTO":2,"PORTERO":null,"TIPO":"normal","MINUTO":"27","EQUIPO":"local"}],"EQUIPO_CASA":{"CODCLUB":6445,"CODCLUB2":15548283,"CODEQUIPO":18493294,"NOMBRE_CLUB":"ESCOLA DE FUTBOL PREMIER BARCELONA","NOMBRE_CLUB_URL":"escola-de-futbol-premier-barcelona","NOMBRE_EQUIPO":"ESCOLA DE FUTBOL PREMIER BARCELONA E","NOMBRE_EQUIPO_URL":"escola-de-futbol-premier-barcelona-e","NOMBRE":"00100_0000754057_premierbcn_200x200.png","NOMBRE_ABREVIADO_URL":"72b","CODGRUPO":41654285,"TITULARES":[{"NOMBRE":"JOEL","LICENCIA":"12","DORSAL":"1","CODPARTICIPANTE":"38401582","FECHA_NACIMIENTO":2,"PORTERO":1},{"NOMBRE":"BIEL","LICENCIA":"12","DORSAL":"6","CODPARTICIPANTE":"38401888","FECHA_NACIMIENTO":2,"PORTERO":null},{"NOMBRE":"PABLO","LICENCIA":"12","DORSAL":"7","CODPARTICIPANTE":"38745696","FECHA_NACIMIENTO":2,"PORTERO":null},{"NOMBRE":"NICOLÁS JESÚS","LICENCIA":"12","DORSAL":"8","CODPARTICIPANTE":"39831128","FECHA_NACIMIENTO":2,"PORTERO":null},{"NOMBRE":"MARTI","LICENCIA":"12","DORSAL":"10","CODPARTICIPANTE":"41161641","FECHA_NACIMIENTO":2,"PORTERO":null},{"NOMBRE":"OLIVER","LICENCIA":"12","DORSAL":"16","CODPARTICIPANTE":"38402178","FECHA_NACIMIENTO":2,"PORTERO":null},{"NOMBRE":"DAVID","LICENCIA":"12","DORSAL":"31","CODPARTICIPANTE":"42484694","FECHA_NACIMIENTO":2,"PORTERO":null}],"SUPLENTES":[{"NOMBRE":"GERARD","LICENCIA":"12","DORSAL":"4","CODPARTICIPANTE":"45232765","FECHA_NACIMIENTO":1,"PORTERO":null},{"NOMBRE":"MATIAS","LICENCIA":"12","DORSAL":"9","CODPARTICIPANTE":"38546021","FECHA_NACIMIENTO":2,"PORTERO":null},{"NOMBRE":"IKER","LICENCIA":"12","DORSAL":"14","CODPARTICIPANTE":"35266681","FECHA_NACIMIENTO":1,"PORTERO":null}],"COSTECNIC":{"Entrenador Titular":"RUBEN"},"SUSTITUCIONES":[],"SANCIONES":[]},"EQUIPO_FUERA":{"CODCLUB":1194,"CODCLUB2":1194,"CODEQUIPO":38045,"NOMBRE_CLUB":"SARRIA, C.P.","NOMBRE_CLUB_URL":"sarria-cp","NOMBRE_EQUIPO":"SARRIÀ, C.P. B","NOMBRE_EQUIPO_URL":"sarria-cp-b","NOMBRE":"00100_0000388904_00100_0000337753_escut-cp-sarria-1952.png","NOMBRE_ABREVIADO_URL":"72b","CODGRUPO":41653927,"TITULARES":[{"NOMBRE":"ERIC","LICENCIA":"12","DORSAL":"1","CODPARTICIPANTE":"39248464","FECHA_NACIMIENTO":1,"PORTERO":1},{"NOMBRE":"DIEGO","LICENCIA":"12","DORSAL":"4","CODPARTICIPANTE":"39975095","FECHA_NACIMIENTO":1,"PORTERO":null},{"NOMBRE":"ALDO","LICENCIA":"12","DORSAL":"5","CODPARTICIPANTE":"38871868","FECHA_NACIMIENTO":1,"PORTERO":null},{"NOMBRE":"BRUNO","LICENCIA":"12","DORSAL":"6","CODPARTICIPANTE":"40278081","FECHA_NACIMIENTO":1,"PORTERO":null},{"NOMBRE":"MIQUEL","LICENCIA":"12","DORSAL":"9","CODPARTICIPANTE":"38449821","FECHA_NACIMIENTO":1,"PORTERO":null},{"NOMBRE":"ALBERT","LICENCIA":"12","DORSAL":"10","CODPARTICIPANTE":"45021396","FECHA_NACIMIENTO":1,"PORTERO":null},{"NOMBRE":"IBAI","LICENCIA":"12","DORSAL":"19","CODPARTICIPANTE":"41124630","FECHA_NACIMIENTO":1,"PORTERO":null}],"SUPLENTES":[{"NOMBRE":"FRANCESC","LICENCIA":"12","DORSAL":"8","CODPARTICIPANTE":"45021868","FECHA_NACIMIENTO":1,"PORTERO":null}],"COSTECNIC":{"Entrenador Titular":"SERGIO"},"SUSTITUCIONES":[],"SANCIONES":[]}},"codacta":"3110079","titulars_local":[{"codparticipant":38401582,"codequip":18493294,"dorsal":1,"titularitats":1,"porter":1,"nom":"JOEL","any":2014,"partits":1,"nom_equip":"ESCOLA DE FUTBOL PREMIER BARCELONA E","colorequipacio1":"#FF0000","colorequipacio2":"#FFFF00"},{"codparticipant":45232765,"codequip":18493294,"dorsal":4,"titularitats":0,"porter":null,"nom":"GERARD","any":2013,"partits":1,"nom_equip":"ESCOLA DE FUTBOL PREMIER BARCELONA E","colorequipacio1":"#FF0000","colorequipacio2":"#FFFF00"},{"codparticipant":38401888,"codequip":18493294,"dorsal":6,"titularitats":1,"porter":null,"nom":"BIEL","any":2014,"partits":1,"nom_equip":"ESCOLA DE FUTBOL PREMIER BARCELONA E","colorequipacio1":"#FF0000","colorequipacio2":"#FFFF00"},{"codparticipant":38745696,"codequip":18493294,"dorsal":7,"titularitats":1,"porter":null,"nom":"PABLO","any":2014,"partits":1,"nom_equip":"ESCOLA DE FUTBOL PREMIER BARCELONA E","colorequipacio1":"#FF0000","colorequipacio2":"#FFFF00"},{"codparticipant":39831128,"codequip":18493294,"dorsal":8,"titularitats":1,"porter":null,"nom":"NICOLÁS JESÚS","any":2014,"partits":1,"nom_equip":"ESCOLA DE FUTBOL PREMIER BARCELONA E","colorequipacio1":"#FF0000","colorequipacio2":"#FFFF00"},{"codparticipant":38546021,"codequip":18493294,"dorsal":9,"titularitats":0,"porter":null,"nom":"MATIAS","any":2014,"partits":1,"nom_equip":"ESCOLA DE FUTBOL PREMIER BARCELONA E","colorequipacio1":"#FF0000","colorequipacio2":"#FFFF00"},{"codparticipant":41161641,"codequip":18493294,"dorsal":10,"titularitats":1,"porter":null,"nom":"MARTI","any":2014,"partits":1,"nom_equip":"ESCOLA DE FUTBOL PREMIER BARCELONA E","colorequipacio1":"#FF0000","colorequipacio2":"#FFFF00"},{"codparticipant":35266681,"codequip":18493294,"dorsal":14,"titularitats":0,"porter":null,"nom":"IKER","any":2013,"partits":1,"nom_equip":"ESCOLA DE FUTBOL PREMIER BARCELONA E","colorequipacio1":"#FF0000","colorequipacio2":"#FFFF00"},{"codparticipant":38402178,"codequip":18493294,"dorsal":16,"titularitats":1,"porter":null,"nom":"OLIVER","any":2014,"partits":1,"nom_equip":"ESCOLA DE FUTBOL PREMIER BARCELONA E","colorequipacio1":"#FF0000","colorequipacio2":"#FFFF00"},{"codparticipant":42484694,"codequip":18493294,"dorsal":31,"titularitats":1,"porter":null,"nom":"DAVID","any":2014,"partits":1,"nom_equip":"ESCOLA DE FUTBOL PREMIER BARCELONA E","colorequipacio1":"#FF0000","colorequipacio2":"#FFFF00"}],"titulars_visitant":[{"codparticipant":39248464,"codequip":38045,"dorsal":1,"titularitats":1,"porter":1,"nom":"ERIC","any":2013,"partits":1,"nom_equip":"SARRIÀ, C.P. B","colorequipacio1":"#FF0000","colorequipacio2":"#FFFF00"},{"codparticipant":39975095,"codequip":38045,"dorsal":4,"titularitats":1,"porter":null,"nom":"DIEGO","any":2013,"partits":1,"nom_equip":"SARRIÀ, C.P. B","colorequipacio1":"#FF0000","colorequipacio2":"#FFFF00"},{"codparticipant":38871868,"codequip":38045,"dorsal":5,"titularitats":1,"porter":null,"nom":"ALDO","any":2013,"partits":1,"nom_equip":"SARRIÀ, C.P. B","colorequipacio1":"#FF0000","colorequipacio2":"#FFFF00"},{"codparticipant":40278081,"codequip":38045,"dorsal":6,"titularitats":1,"porter":null,"nom":"BRUNO","any":2013,"partits":1,"nom_equip":"SARRIÀ, C.P. B","colorequipacio1":"#FF0000","colorequipacio2":"#FFFF00"},{"codparticipant":45021868,"codequip":38045,"dorsal":8,"titularitats":0,"porter":null,"nom":"FRANCESC","any":2013,"partits":1,"nom_equip":"SARRIÀ, C.P. B","colorequipacio1":"#FF0000","colorequipacio2":"#FFFF00"},{"codparticipant":38449821,"codequip":38045,"dorsal":9,"titularitats":1,"porter":null,"nom":"MIQUEL","any":2013,"partits":1,"nom_equip":"SARRIÀ, C.P. B","colorequipacio1":"#FF0000","colorequipacio2":"#FFFF00"},{"codparticipant":45021396,"codequip":38045,"dorsal":10,"titularitats":1,"porter":null,"nom":"ALBERT","any":2013,"partits":1,"nom_equip":"SARRIÀ, C.P. B","colorequipacio1":"#FF0000","colorequipacio2":"#FFFF00"},{"codparticipant":41124630,"codequip":38045,"dorsal":19,"titularitats":1,"porter":null,"nom":"IBAI","any":2013,"partits":1,"nom_equip":"SARRIÀ, C.P. B","colorequipacio1":"#FF0000","colorequipacio2":"#FFFF00"}],"menuFollowTeams":[{"label":"BEN A","href":"/classificacio?id=45412613"},{"label":"BEN B","href":"/classificacio?id=45413087"},{"label":"BEN C","href":"/classificacio?id=45412812"},{"label":"BEN D","href":"/classificacio?id=45293518"},{"label":"BEN E","href":"/classificacio?id=45293333"}]}