{"data":{"INFO":{"CODGRUPO":"45293333","GOLES_CASA":"7","GOLES_FUERA":"6","PENALTIS_CASA":null,"PENALTIS_FUERA":null,"CODACTA":"3133254","COD_COMPETICION":43990766,"NOM_COMPETICION":"BENJAMÍ 7 TERCERA DIVISIÓ","NOM_COMPETICION_URL":"benjami-7-tercera-divisio","COD_GRUPO":45293333,"GRUPO":"GRUP 1","GRUPO_URL":"grup-1","CODEQUIPO_CASA":"41598","CODEQUIPO_FUERA":"28485868","JORNADA":"1","CODIGO_CAMPO":"383","COMIENZO1":"2022-10-09 09:00:00","SUSPENDIDO":"0","NOMBRE":"CAMP DE FUTBOL CEM GUINARDÓ","DIRECCION":"rda. del Guinardó, 141","TEMP_NOMBRE":"2223","TEMP_LARGO":"TEMPORADA 2022-2023","CIUDAD":"Barcelona","ESTADO":"4"},"ARBITROS":[{"CODTIPO_ARBITRO":"1","CODARBITRO":"3327752","NOMBRE_ARBITRO":"DANIEL","NOMBRE":"Barcelona3"}],"GOLES":[{"NOMBRE":"PERE","LICENCIA":"12","DORSAL":"2","CODPARTICIPANTE":"45064016","FECHA_NACIMIENTO":2,"PORTERO":null,"TIPO":"normal","MINUTO":"4","EQUIPO":"visitante"},{"NOMBRE":"PERE","LICENCIA":"12","DORSAL":"2","CODPARTICIPANTE":"45064016","FECHA_NACIMIENTO":2,"PORTERO":null,"TIPO":"normal","MINUTO":"15","EQUIPO":"visitante"},{"NOMBRE":"PERE","LICENCIA":"12","DORSAL":"2","CODPARTICIPANTE":"45064016","FECHA_NACIMIENTO":2,"PORTERO":null,"TIPO":"penalti","MINUTO":"24","EQUIPO":"visitante"},{"NOMBRE":"PERE","LICENCIA":"12","DORSAL":"2","CODPARTICIPANTE":"45064016","FECHA_NACIMIENTO":2,"PORTERO":null,"TIPO":"normal","MINUTO":"33","EQUIPO":"visitante"},{"NOMBRE":"IAN RIPOLLES","LICENCIA":"12","DORSAL":"9","CODPARTICIPANTE":"45114029","FECHA_NACIMIENTO":2,"PORTERO":null,"TIPO":"normal","MINUTO":"6","EQUIPO":"visitante"},{"NOMBRE":"IAN RIPOLLES","LICENCIA":"12","DORSAL":"9","CODPARTICIPANTE":"45114029","FECHA_NACIMIENTO":2,"PORTERO":null,"TIPO":"normal","MINUTO":"42","EQUIPO":"visitante"},{"NOMBRE":"JAKE AUSTIN","LICENCIA":"12","DORSAL":"68","CODPARTICIPANTE":"38787719","FECHA_NACIMIENTO":1,"PORTERO":null,"TIPO":"normal","MINUTO":"42","EQUIPO":"local"},{"NOMBRE":"JOAN","LICENCIA":"12","DORSAL":"89","CODPARTICIPANTE":"36220024","FECHA_NACIMIENTO":1,"PORTERO":null,"TIPO":"normal","MINUTO":"2","EQUIPO":"local"},{"NOMBRE":"JOAN","LICENCIA":"12","DORSAL":"89","CODPARTICIPANTE":"36220024","FECHA_NACIMIENTO":1,"PORTERO":null,"TIPO":"normal","MINUTO":"6","EQUIPO":"local"},{"NOMBRE":"JOAN","LICENCIA":"12","DORSAL":"89","CODPARTICIPANTE":"36220024","FECHA_NACIMIENTO":1,"PORTERO":null,"TIPO":"normal","MINUTO":"15","EQUIPO":"local"},{"NOMBRE":"JOAN","LICENCIA":"12","DORSAL":"89","CODPARTICIPANTE":"36220024","FECHA_NACIMIENTO":1,"PORTERO":null,"TIPO":"normal","MINUTO":"24","EQUIPO":"local"},{"NOMBRE":"JOAN","LICENCIA":"12","DORSAL":"89","CODPARTICIPANTE":"36220024","FECHA_NACIMIENTO":1,"PORTERO":null,"TIPO":"normal","MINUTO":"30","EQUIPO":"local"},{"NOMBRE":"JOAN","LICENCIA":"12","DORSAL":"89","CODPARTICIPANTE":"36220024","FECHA_NACIMIENTO":1,"PORTERO":null,"TIPO":"normal","MINUTO":"44","EQUIPO":"local"}],"EQUIPO_CASA":{"CODCLUB":1032,"CODCLUB2":1032,"CODEQUIPO":41598,"NOMBRE_CLUB":"MARTINENC, F.C.","NOMBRE_CLUB_URL":"martinenc-fc","NOMBRE_EQUIPO":"MARTINENC, F.C. F","NOMBRE_EQUIPO_URL":"martinenc-fc-f","NOMBRE":"00100_0000577607_martinenc-200x200.png","NOMBRE_ABREVIADO_URL":"73b","CODGRUPO":42202269,"TITULARES":[{"NOMBRE":"ANGEL ALFREDO","LICENCIA":"12","DORSAL":"5","CODPARTICIPANTE":"45486740","FECHA_NACIMIENTO":1,"PORTERO":1},{"NOMBRE":"MARC JAIDER","LICENCIA":"12","DORSAL":"18","CODPARTICIPANTE":"45763504","FECHA_NACIMIENTO":1,"PORTERO":null},{"NOMBRE":"YOUSEF","LICENCIA":"12","DORSAL":"54","CODPARTICIPANTE":"42065190","FECHA_NACIMIENTO":1,"PORTERO":null},{"NOMBRE":"BIEL","LICENCIA":"12","DORSAL":"55","CODPARTICIPANTE":"42320267","FECHA_NACIMIENTO":1,"PORTERO":null},{"NOMBRE":"JAKE AUSTIN","LICENCIA":"12","DORSAL":"68","CODPARTICIPANTE":"38787719","FECHA_NACIMIENTO":1,"PORTERO":null},{"NOMBRE":"JOAN","LICENCIA":"12","DORSAL":"89","CODPARTICIPANTE":"36220024","FECHA_NACIMIENTO":1,"PORTERO":null},{"NOMBRE":"HOUSSAM","LICENCIA":"12","DORSAL":"99","CODPARTICIPANTE":"35325112","FECHA_NACIMIENTO":1,"PORTERO":null}],"SUPLENTES":[{"NOMBRE":"PABLO","LICENCIA":"12","DORSAL":"44","CODPARTICIPANTE":"45382828","FECHA_NACIMIENTO":2,"PORTERO":null},{"NOMBRE":"MIQUEL","LICENCIA":"12","DORSAL":"86","CODPARTICIPANTE":"45082013","FECHA_NACIMIENTO":1,"PORTERO":null}],"COSTECNIC":{"Entrenador Titular":"MANUEL"},"SUSTITUCIONES":[],"SANCIONES":[]},"EQUIPO_FUERA":{"CODCLUB":1194,"CODCLUB2":1194,"CODEQUIPO":28485868,"NOMBRE_CLUB":"SARRIA, C.P.","NOMBRE_CLUB_URL":"sarria-cp","NOMBRE_EQUIPO":"SARRIÀ, C.P. E","NOMBRE_EQUIPO_URL":"sarria-cp-e","NOMBRE":"00100_0000388904_00100_0000337753_escut-cp-sarria-1952.png","NOMBRE_ABREVIADO_URL":"73b","CODGRUPO":42202269,"TITULARES":[{"NOMBRE":"PERE","LICENCIA":"12","DORSAL":"2","CODPARTICIPANTE":"45064016","FECHA_NACIMIENTO":2,"PORTERO":null},{"NOMBRE":"ÀLEX","LICENCIA":"12","DORSAL":"4","CODPARTICIPANTE":"44712805","FECHA_NACIMIENTO":2,"PORTERO":null},{"NOMBRE":"DANIEL PASCUAL","LICENCIA":"12","DORSAL":"5","CODPARTICIPANTE":"45067972","FECHA_NACIMIENTO":2,"PORTERO":null},{"NOMBRE":"IGNACIO","LICENCIA":"12","DORSAL":"7","CODPARTICIPANTE":"44886621","FECHA_NACIMIENTO":2,"PORTERO":null},{"NOMBRE":"ROMAN","LICENCIA":"12","DORSAL":"8","CODPARTICIPANTE":"45851175","FECHA_NACIMIENTO":1,"PORTERO":null},{"NOMBRE":"IAN RIPOLLES","LICENCIA":"12","DORSAL":"9","CODPARTICIPANTE":"45114029","FECHA_NACIMIENTO":2,"PORTERO":null},{"NOMBRE":"SAMY","LICENCIA":"12","DORSAL":"14","CODPARTICIPANTE":"36137335","FECHA_NACIMIENTO":1,"PORTERO":1}],"SUPLENTES":[{"NOMBRE":"BERNAT","LICENCIA":"12","DORSAL":"10","CODPARTICIPANTE":"44885817","FECHA_NACIMIENTO":1,"PORTERO":null}],"COSTECNIC":{"Auxiliar":"MIKHAIL"},"SUSTITUCIONES":[],"SANCIONES":[]}},"codacta":"3133254","titulars_local":[{"codparticipant":45486740,"codequip":41598,"dorsal":5,"titularitats":1,"porter":1,"nom":"ANGEL ALFREDO","any":2013,"partits":1,"nom_equip":"MARTINENC, F.C. F","colorequipacio1":"#FF0000","colorequipacio2":null},{"codparticipant":45763504,"codequip":41598,"dorsal":18,"titularitats":1,"porter":null,"nom":"MARC JAIDER","any":2013,"partits":1,"nom_equip":"MARTINENC, F.C. F","colorequipacio1":"#FF0000","colorequipacio2":null},{"codparticipant":45382828,"codequip":41598,"dorsal":44,"titularitats":0,"porter":null,"nom":"PABLO","any":2014,"partits":1,"nom_equip":"MARTINENC, F.C. F","colorequipacio1":"#FF0000","colorequipacio2":null},{"codparticipant":42065190,"codequip":41598,"dorsal":54,"titularitats":1,"porter":null,"nom":"YOUSEF","any":2013,"partits":1,"nom_equip":"MARTINENC, F.C. F","colorequipacio1":"#FF0000","colorequipacio2":null},{"codparticipant":42320267,"codequip":41598,"dorsal":55,"titularitats":1,"porter":null,"nom":"BIEL","any":2013,"partits":1,"nom_equip":"MARTINENC, F.C. F","colorequipacio1":"#FF0000","colorequipacio2":null},{"codparticipant":38787719,"codequip":41598,"dorsal":68,"titularitats":1,"porter":null,"nom":"JAKE AUSTIN","any":2013,"partits":1,"nom_equip":"MARTINENC, F.C. F","colorequipacio1":"#FF0000","colorequipacio2":null},{"codparticipant":45082013,"codequip":41598,"dorsal":86,"titularitats":0,"porter":null,"nom":"MIQUEL","any":2013,"partits":1,"nom_equip":"MARTINENC, F.C. F","colorequipacio1":"#FF0000","colorequipacio2":null},{"codparticipant":36220024,"codequip":41598,"dorsal":89,"titularitats":1,"porter":null,"nom":"JOAN","any":2013,"partits":1,"nom_equip":"MARTINENC, F.C. F","colorequipacio1":"#FF0000","colorequipacio2":null},{"codparticipant":35325112,"codequip":41598,"dorsal":99,"titularitats":1,"porter":null,"nom":"HOUSSAM","any":2013,"partits":1,"nom_equip":"MARTINENC, F.C. F","colorequipacio1":"#FF0000","colorequipacio2":null}],"titulars_visitant":[{"codparticipant":45064016,"codequip":28485868,"dorsal":2,"titularitats":1,"porter":null,"nom":"PERE","any":2014,"partits":1,"nom_equip":"SARRIÀ, C.P. E","colorequipacio1":"#FF0000","colorequipacio2":"#FFFF00"},{"codparticipant":44712805,"codequip":28485868,"dorsal":4,"titularitats":1,"porter":null,"nom":"ÀLEX","any":2014,"partits":1,"nom_equip":"SARRIÀ, C.P. E","colorequipacio1":"#FF0000","colorequipacio2":"#FFFF00"},{"codparticipant":45067972,"codequip":28485868,"dorsal":5,"titularitats":1,"porter":null,"nom":"DANIEL PASCUAL","any":2014,"partits":1,"nom_equip":"SARRIÀ, C.P. E","colorequipacio1":"#FF0000","colorequipacio2":"#FFFF00"},{"codparticipant":44886621,"codequip":28485868,"dorsal":7,"titularitats":1,"porter":null,"nom":"IGNACIO","any":2014,"partits":1,"nom_equip":"SARRIÀ, C.P. E","colorequipacio1":"#FF0000","colorequipacio2":"#FFFF00"},{"codparticipant":45851175,"codequip":28485868,"dorsal":8,"titularitats":1,"porter":null,"nom":"ROMAN","any":2013,"partits":1,"nom_equip":"SARRIÀ, C.P. E","colorequipacio1":"#FF0000","colorequipacio2":"#FFFF00"},{"codparticipant":45114029,"codequip":28485868,"dorsal":9,"titularitats":1,"porter":null,"nom":"IAN RIPOLLES","any":2014,"partits":1,"nom_equip":"SARRIÀ, C.P. E","colorequipacio1":"#FF0000","colorequipacio2":"#FFFF00"},{"codparticipant":44885817,"codequip":28485868,"dorsal":10,"titularitats":0,"porter":null,"nom":"BERNAT","any":2013,"partits":1,"nom_equip":"SARRIÀ, C.P. E","colorequipacio1":"#FF0000","colorequipacio2":"#FFFF00"},{"codparticipant":36137335,"codequip":28485868,"dorsal":14,"titularitats":1,"porter":1,"nom":"SAMY","any":2013,"partits":1,"nom_equip":"SARRIÀ, C.P. E","colorequipacio1":"#FF0000","colorequipacio2":"#FFFF00"}],"menuFollowTeams":[{"label":"BEN A","href":"/classificacio?id=45412613"},{"label":"BEN B","href":"/classificacio?id=45413087"},{"label":"BEN C","href":"/classificacio?id=45412812"},{"label":"BEN D","href":"/classificacio?id=45293518"},{"label":"BEN E","href":"/classificacio?id=45293333"}]}