{"data":[{"codparticipant":45895538,"codequip":37812,"dorsal":3,"titularitats":9,"porter":null,"nom":"YASSINE","any":2014,"partits":10,"nom_equip":"ALZAMORA, C.F. A"},{"codparticipant":35327671,"codequip":37812,"dorsal":4,"titularitats":6,"porter":null,"nom":"VICTOR","any":2013,"partits":11,"nom_equip":"ALZAMORA, C.F. A"},{"codparticipant":34126452,"codequip":37812,"dorsal":5,"titularitats":11,"porter":null,"nom":"IZAN","any":2013,"partits":11,"nom_equip":"ALZAMORA, C.F. A"},{"codparticipant":34126547,"codequip":37812,"dorsal":6,"titularitats":6,"porter":null,"nom":"ERIC POL","any":2013,"partits":11,"nom_equip":"ALZAMORA, C.F. A"},{"codparticipant":39375308,"codequip":37812,"dorsal":8,"titularitats":3,"porter":null,"nom":"FRANCISCO JAVIER","any":2013,"partits":11,"nom_equip":"ALZAMORA, C.F. A"},{"codparticipant":34126201,"codequip":37812,"dorsal":9,"titularitats":9,"porter":null,"nom":"MARC","any":2013,"partits":9,"nom_equip":"ALZAMORA, C.F. A"},{"codparticipant":39716812,"codequip":37812,"dorsal":11,"titularitats":11,"porter":null,"nom":"SANTIAGO","any":2013,"partits":11,"nom_equip":"ALZAMORA, C.F. A"},{"codparticipant":34126376,"codequip":37812,"dorsal":12,"titularitats":9,"porter":null,"nom":"NICOLAS","any":2013,"partits":10,"nom_equip":"ALZAMORA, C.F. A"},{"codparticipant":39525322,"codequip":37812,"dorsal":13,"titularitats":11,"porter":1,"nom":"MAJD","any":2013,"partits":11,"nom_equip":"ALZAMORA, C.F. A"},{"codparticipant":45731234,"codequip":37812,"dorsal":71,"titularitats":2,"porter":null,"nom":"CARLOS DANIEL","any":2013,"partits":11,"nom_equip":"ALZAMORA, C.F. A"}],"codequip":"37812","codgroup":"45413087","menuFollowTeams":[{"label":"BEN A","href":"/classificacio?id=45412613"},{"label":"BEN B","href":"/classificacio?id=45413087"},{"label":"BEN C","href":"/classificacio?id=45412812"},{"label":"BEN D","href":"/classificacio?id=45293518"},{"label":"BEN E","href":"/classificacio?id=45293333"}]}