{"data":[{"codparticipant":38636187,"codequip":7004366,"dorsal":1,"titularitats":30,"porter":1,"nom":"MOHAMED ALI","any":2014,"partits":30,"nom_equip":"SINGUERLIN, C.F. B"},{"codparticipant":45222784,"codequip":7004366,"dorsal":3,"titularitats":20,"porter":null,"nom":"AYMAN","any":2014,"partits":29,"nom_equip":"SINGUERLIN, C.F. B"},{"codparticipant":38635767,"codequip":7004366,"dorsal":5,"titularitats":12,"porter":null,"nom":"IAN","any":2014,"partits":30,"nom_equip":"SINGUERLIN, C.F. B"},{"codparticipant":38635898,"codequip":7004366,"dorsal":6,"titularitats":24,"porter":null,"nom":"JOEL","any":2014,"partits":30,"nom_equip":"SINGUERLIN, C.F. B"},{"codparticipant":38635991,"codequip":7004366,"dorsal":7,"titularitats":25,"porter":null,"nom":"ABEL","any":2014,"partits":30,"nom_equip":"SINGUERLIN, C.F. B"},{"codparticipant":38635978,"codequip":7004366,"dorsal":8,"titularitats":27,"porter":null,"nom":"BLAI","any":2014,"partits":30,"nom_equip":"SINGUERLIN, C.F. B"},{"codparticipant":36194029,"codequip":7004366,"dorsal":9,"titularitats":25,"porter":null,"nom":"ASIER","any":2014,"partits":29,"nom_equip":"SINGUERLIN, C.F. B"},{"codparticipant":38701629,"codequip":7004366,"dorsal":10,"titularitats":24,"porter":null,"nom":"ABRAHAM","any":2014,"partits":30,"nom_equip":"SINGUERLIN, C.F. B"},{"codparticipant":38635546,"codequip":7004366,"dorsal":11,"titularitats":19,"porter":null,"nom":"JAVIER","any":2014,"partits":29,"nom_equip":"SINGUERLIN, C.F. B"},{"codparticipant":45415500,"codequip":7004366,"dorsal":12,"titularitats":4,"porter":null,"nom":"RAFAEL","any":2014,"partits":19,"nom_equip":"SINGUERLIN, C.F. B"}],"codequip":"7004366","codgroup":"45412812","menuFollowTeams":[{"label":"BEN A","href":"/classificacio?id=45412613"},{"label":"BEN B","href":"/classificacio?id=45413087"},{"label":"BEN C","href":"/classificacio?id=45412812"},{"label":"BEN D","href":"/classificacio?id=45293518"},{"label":"BEN E","href":"/classificacio?id=45293333"}]}